selenium_components/__init__.py
selenium_components/base_page.py
selenium_components-0.1.dist-info/DESCRIPTION.rst
selenium_components-0.1.dist-info/METADATA
selenium_components-0.1.dist-info/RECORD
selenium_components-0.1.dist-info/WHEEL
selenium_components-0.1.dist-info/metadata.json
selenium_components-0.1.dist-info/top_level.txt
